brainfeatures/__init__.py
brainfeatures/version.py
brainfeatures/analysis/__init__.py
brainfeatures/analysis/analyze.py
brainfeatures/data_set/__init__.py
brainfeatures/data_set/abstract_data_set.py
brainfeatures/data_set/tuh_abnormal.py
brainfeatures/decoding/__init__.py
brainfeatures/decoding/decode.py
brainfeatures/experiment/__init__.py
brainfeatures/experiment/experiment.py
brainfeatures/experiment/suite.py
brainfeatures/feature_generation/__init__.py
brainfeatures/feature_generation/abstract_feature_generator.py
brainfeatures/feature_generation/feature_generator.py
brainfeatures/feature_generation/features_frequency.py
brainfeatures/feature_generation/features_phase.py
brainfeatures/feature_generation/features_time.py
brainfeatures/feature_generation/features_wavelets.py
brainfeatures/feature_generation/frequency_feature_generator.py
brainfeatures/feature_generation/generate_features.py
brainfeatures/feature_generation/generate_mne_features.py
brainfeatures/feature_generation/phase_feature_generator.py
brainfeatures/feature_generation/time_feature_generator.py
brainfeatures/feature_generation/wavelet_feature_generator.py
brainfeatures/preprocessing/__init__.py
brainfeatures/preprocessing/preprocess_raw.py
brainfeatures/preprocessing/rules.py
brainfeatures/utils/__init__.py
brainfeatures/utils/data_util.py
brainfeatures/utils/file_util.py
brainfeatures/utils/sun_grid_engine_util.py
brainfeatures/visualization/__init__.py
brainfeatures/visualization/visualize.py
Brainfeatures-0.0.4.dist-info/LICENSE.txt
Brainfeatures-0.0.4.dist-info/METADATA
Brainfeatures-0.0.4.dist-info/WHEEL
Brainfeatures-0.0.4.dist-info/top_level.txt
Brainfeatures-0.0.4.dist-info/RECORD
