Metadata-Version: 2.1
Name: Brainfeatures
Version: 0.0.4
Summary: A toolbox to decode raw time-domain EEG using features.
Home-page: https://github.com/gemeinl/brainfeatures
Author: Lukas Alexander Wilhelm Gemein
Author-email: l.gemein@gmail.com
License: BSD 3-Clause
Keywords: eeg features brain-state-decoding
Platform: UNKNOWN
Classifier: Development Status :: 3 - Alpha
Classifier: Intended Audience :: Developers
Classifier: Intended Audience :: Science/Research
Classifier: Topic :: Software Development :: Build Tools
Classifier: Topic :: Scientific/Engineering :: Artificial Intelligence
Classifier: License :: OSI Approved :: BSD License
Classifier: Programming Language :: Python :: 3.5
Requires-Dist: mne
Requires-Dist: numpy
Requires-Dist: pandas
Requires-Dist: scipy
Requires-Dist: resampy
Requires-Dist: matplotlib
Requires-Dist: h5py
Requires-Dist: pywavelets
Requires-Dist: joblib
Requires-Dist: scikit-learn
Requires-Dist: rfpimp
